checkout_time_computer/__init__.py
checkout_time_computer/checkout_time_computer.py
checkout_time_computer-1.0.0.dist-info/LICENCE
checkout_time_computer-1.0.0.dist-info/METADATA
checkout_time_computer-1.0.0.dist-info/WHEEL
checkout_time_computer-1.0.0.dist-info/RECORD
