Metadata-Version: 2.1
Name: checkout-time-computer
Version: 1.0.0
Summary: 
Author: Augustinas Naina
Author-email: augustinas@naina.lt
Requires-Python: >=3.12,<4.0
Classifier: Programming Language :: Python :: 3
Classifier: Programming Language :: Python :: 3.12
